datatransfer/__init__.py
datatransfer/constants.py
datatransfer/driver.py
datatransfer/local_data_transfer.py
datatransfer/rest_client.py
datatransfer/util.py
datatransfer/watcher.py
ftpsync/__init__.py
ftpsync/constants.py
ftpsync/driver.py
ftpsync/ftp_processor.py
ftpsync/ftp_transfer.py
ftpsync/ftp_util.py
ftpsync/rest_driver.py
ftpsync/s3_processor.py
ftpsync/settings.py
ftpsync/sftp_processor.py
scorefastlib/__init__.py
scorefastlib/utils.py
scorefastlib/common/__init__.py
scorefastlib/common/constants.py
scorefastlib/common/rest_client.py
scorefastlib-0.1.3.dist-info/LICENSE
scorefastlib-0.1.3.dist-info/METADATA
scorefastlib-0.1.3.dist-info/WHEEL
scorefastlib-0.1.3.dist-info/top_level.txt
scorefastlib-0.1.3.dist-info/RECORD
