Metadata-Version: 2.1
Name: scorefastlib
Version: 0.1.3
Summary: scorefast customer tool
Home-page: https://github.com/ScoreDataCorporation/scorefast-lib
Author: scorefast
Author-email: ravisharma@scoredata.com
License: UNKNOWN
Platform: UNKNOWN
Classifier: Programming Language :: Python :: 3
Classifier: License :: OSI Approved :: MIT License
Classifier: Operating System :: OS Independent
